{"result_sugestion": {"cutoff": ""}, "result_user": {"analysis": ["28EY", "28EH", "28DY", "28DHF", "28D", "16Y", "149H", "142M<sub>3</sub>", "13SEF", "30H", "31FH", "31FYY", "57S", "13SE", "51R<sub>2</sub>", "38L", "37YV", "37FL<sub>2</sub>", "37D<sub>2</sub>", "47F", "11STS", "77N+85VG", "77N", "74R", "71K", "71E", "70QKA", "70QK", "70QE", "9H", "70QQ", "96HK", "98Q", "52PL<sub>3</sub>", "45EV", "3P<sub>4</sub>", "96Y<sub>2</sub>", "23L", "185I", "167H<sub>2</sub>", "160S", "160D", "56E", "56E<sup>DR11</sup>", "178M", "28D", "65LK", "96A", "70DA", "65LE", "55RL<sub>3</sub>", "55PPD", "55PPA", "55PP", "56EE<sup>DR11</sup>", "57D", "57DE<sup>DP</sup>", "58EE<sup>DP</sup>", "56EE"], "cutoff": "10238"}}