{"result_sugestion": {"cutoff": ""}, "result_user": {"analysis": ["193PL", "199V", "211T", "267QE", "270C", "275K", "43Q+62GE", "44RMA", "44RT", "44RT+69TNT", "158T", "162DLS", "162GLS", "163LS/G", "163LW+65QIT", "166DG", "166ES", "16S", "184R", "62EE", "62GE", "76ED", "76ESI", "80I", "80I+69TNT", "80I+90A", "80TA", "80TLR", "81ALR", "82LR", "82LR+138M", "82LR+138T", "82LR+144QR", "82LR+145R", "73AN", "62GK", "62GRN", "65GK", "65RNA+80I", "66IC", "66IF", "66IF+163TEW", "66KH", "71ATD", "71KA", "71SA", "71TD", "71TN", "14W", "103M", "95V", "97N", "107W", "99S", "9D", "82LR+145RA", "82LR+90A", "144QL"], "cutoff": "1069"}}