{"result_sugestion": {"cutoff": ""}, "result_user": {"analysis": ["163R", "152RR", "152T", "152W", "156DA", "163L", "163LE", "163LS/G", "163LW", "163LW+65QIT", "163RW", "166ES", "211T", "193PV", "152HA", "186R", "17S", "177KT", "177DT", "170RH", "16S", "184H", "219W", "62GE", "56R", "45KE", "44RT+69TNT", "44RT", "44RMA", "102H", "103L", "103M", "107W", "113YD", "113YN", "114Q", "14W", "149TAH", "145RT", "151AHE", "138MI+79GT", "138K", "11AV", "116S", "116L", "21H", "184R", "80K+14R", "80K", "80I+69TNT", "79GT+90D", "77NGT", "80TA", "76VRN", "76ESI", "76EG", "76ED", "76ANT", "74Y", "73TVS", "245AS", "73ID", "80TLR", "82LR+144QR", "35Q", "9T", "9H", "9F", "82LR+138T", "97W", "97N", "97I", "95V", "94I", "90D", "76ET", "71TN", "275G", "275K", "24T", "248M", "73AN", "30G", "32L", "275EL", "62QE", "62QE+56G", "65QKR", "62LQ", "71TD", "71SA", "71KA", "69RT", "66NM", "270C", "66NH", "66IS", "66IF+163TEW", "66IF", "65RNA+80I", "65RK"], "cutoff": "1020"}}