{"result_sugestion": {"cutoff": ""}, "result_user": {"analysis": ["40YD<sub>2</sub>", "4Q", "56E<sup>DR11</sup>", "56EE<sup>DR11</sup>", "57DE", "57DE<sup>DP</sup>", "57S", "58EE<sup>DP</sup>", "67F", "70DK", "70DR", "70DRA", "70QE", "70QKA", "71E", "74L", "78V<sub>2</sub>", "70D", "70DA", "75S<sub>3</sub>", "98E", "30Y", "37YA", "40ERV", "70GT", "67VT", "66IT", "66IL", "66ER", "66DR", "66D", "61FT<sub>4</sub>", "56PA", "55RL<sub>3</sub>", "55PPD", "55PPA", "55PP", "52PL<sub>3</sub>", "47QL<sub>5</sub>", "47KHL", "45GE<sub>3</sub>", "45EV", "40GR<sub>3</sub>", "96Y<sub>2</sub>", "26L", "116V", "125G", "129H", "9F", "87F", "84QL<sub>3</sub>", "25FT", "77T", "37YV", "75IL", "74EL", "70RT", "135G", "13GM", "160AE", "160S", "167H<sub>2</sub>", "175E", "185I", "76L", "133RS", "37L", "57D", "35LV", "65LE", "9H", "76V", "25Q<sub>3</sub>", "181M", "180VMP", "16Y", "13FEY", "37D<sub>2</sub>", "31FYY"], "cutoff": "1090"}}